beets_artistcountry-0.2.0-py3.5-nspkg.pth
beets_artistcountry-0.2.0.dist-info/DESCRIPTION.rst
beets_artistcountry-0.2.0.dist-info/METADATA
beets_artistcountry-0.2.0.dist-info/RECORD
beets_artistcountry-0.2.0.dist-info/WHEEL
beets_artistcountry-0.2.0.dist-info/metadata.json
beets_artistcountry-0.2.0.dist-info/namespace_packages.txt
beets_artistcountry-0.2.0.dist-info/top_level.txt
beetsplug/artistcountry.py
