Metadata-Version: 2.0
Name: beets-artistcountry
Version: 0.2.0
Summary: Beets plugin to retrieve the country of an artist from musicbrainz
Home-page: https://github.com/agrausem/beets-artistcountry
Author: Arnaud Grausem
Author-email: arnaud.grausem@gmail.com
License: MIT
Platform: UNKNOWN
Requires-Dist: beets
Requires-Dist: musicbrainzngs
